redfish_interop_validator/RedfishInteropValidator.py
redfish_interop_validator/RedfishLogo.py
redfish_interop_validator/__init__.py
redfish_interop_validator/config.py
redfish_interop_validator/helper.py
redfish_interop_validator/interop.py
redfish_interop_validator/logger.py
redfish_interop_validator/profile.py
redfish_interop_validator/session.py
redfish_interop_validator/tohtml.py
redfish_interop_validator/traverseInterop.py
redfish_interop_validator/validateResource.py
redfish_interop_validator-2.3.3.dist-info/licenses/AUTHORS.md
redfish_interop_validator-2.3.3.dist-info/licenses/LICENSE.md
redfish_interop_validator-2.3.3.dist-info/METADATA
redfish_interop_validator-2.3.3.dist-info/WHEEL
redfish_interop_validator-2.3.3.dist-info/entry_points.txt
redfish_interop_validator-2.3.3.dist-info/top_level.txt
redfish_interop_validator-2.3.3.dist-info/RECORD
