Metadata-Version: 2.4
Name: redfish_interop_validator
Version: 2.3.3
Summary: Redfish Interop Validator
Home-page: https://github.com/DMTF/Redfish-Interop-Validator
Author: DMTF, https://www.dmtf.org/standards/feedback
License: BSD 3-clause "New" or "Revised License"
Keywords: Redfish
Classifier: Development Status :: 5 - Production/Stable
Classifier: License :: OSI Approved :: BSD License
Classifier: Programming Language :: Python
Classifier: Topic :: Communications
License-File: LICENSE.md
License-File: AUTHORS.md
Requires-Dist: requests
Requires-Dist: beautifulsoup4>=4.6.0
Requires-Dist: lxml
Requires-Dist: jsonschema
Dynamic: author
Dynamic: classifier
Dynamic: description
Dynamic: description-content-type
Dynamic: home-page
Dynamic: keywords
Dynamic: license
Dynamic: license-file
Dynamic: requires-dist
Dynamic: summary
